tafra/__init__.py
tafra/base.py
tafra/csvreader.py
tafra/formatter.py
tafra/group.py
tafra/protocol.py
tafra/py.typed
tafra/version.py
tafra-1.0.10.dist-info/LICENSE
tafra-1.0.10.dist-info/METADATA
tafra-1.0.10.dist-info/WHEEL
tafra-1.0.10.dist-info/top_level.txt
tafra-1.0.10.dist-info/RECORD
