Metadata-Version: 2.1
Name: tafra
Version: 1.0.10
Summary: Tafra: innards of a dataframe
Home-page: https://github.com/petbox-dev/tafra
Author: David S. Fulford
Author-email: petbox.dev@gmail.com
Keywords: tafra,dataframe,sql,group-by,aggregation,performance,minimalist
Classifier: Development Status :: 5 - Production/Stable
Classifier: Intended Audience :: Science/Research
Classifier: Intended Audience :: Education
Classifier: Intended Audience :: Developers
Classifier: Natural Language :: English
Classifier: License :: OSI Approved :: MIT License
Classifier: Programming Language :: Python :: 3.7
Classifier: Programming Language :: Python :: 3.8
Classifier: Programming Language :: Python :: Implementation :: CPython
Classifier: Topic :: Scientific/Engineering
Classifier: Topic :: Scientific/Engineering :: Mathematics
Classifier: Topic :: Software Development :: Libraries
Classifier: Typing :: Typed
Requires-Python: >=3.7
License-File: LICENSE
Requires-Dist: numpy (>=1.17)
Requires-Dist: typing-extensions
